[
	{
		"syntax": "dust_json",
		"version": "1.0"
	},
	{
		"pubGiskard": {
			"memKnowledgeType": "typPublisher",
			"memKnowledgeToken": "Giskard"
		},
		"ctxMiND": {
			"memKnowledgeType": "typContext",
			"memKnowledgePublisher": "pubGiskard",
			"memKnowledgeToken": "MiND",
			"memKnowledgeCommit": 0,
			"memKnowledgeTags": {
				"tagPubtype": "tagPubtypeContext"
			}
		},
		"ctxStream": {
			"memKnowledgeType": "typContext",
			"memKnowledgePublisher": "pubGiskard",
			"memKnowledgeToken": "Stream",
			"memKnowledgeCommit": 0,
			"memKnowledgeTags": {
				"tagPubtype": "tagPubtypeContext"
			}
		},
		
		"typModule": {
			"memKnowledgeType": "typType"
		},
		"memModuleImplementations": {
			"memKnowledgeType": "typMember",
			"memKnowledgeOwner": "typModule",
			"memKnowledgeTags": {
				"tagColl": "tagCollMap",
				"tagValtype": "tagValtypeLink"
			},
			"memMemberKeyType": "typAgent",
			"memMemberLinkType": "typImplementation"
		},
		"tagPubtypeModule": {
			"memKnowledgeType": "typTag",
			"memKnowledgeOwner": "tagPubtype"
		},


		"agtBrain": {
			"memKnowledgeType": "typLogic"
		},

		"typApp": {
			"memKnowledgeType": "typType",
			"memKnowledgeRequires" : [
				"typDialog"
			]
		},
		"memAppConfig": {
			"memKnowledgeType": "typMember",
			"memKnowledgeOwner": "typApp",
			"memKnowledgeTags": {
				"tagColl": "tagCollMap",
				"tagValtype": "tagValtypeBin"
			}
		},
		"memAppBrain": {
			"memKnowledgeType": "typMember",
			"memKnowledgeOwner": "typApp",
			"memKnowledgeTags": {
				"tagValtype": "tagValtypeLink"
			},
			"memMemberLinkType": "agtBrain"
		},
		"memAppStreamProvider": {
			"memKnowledgeType": "typMember",
			"memKnowledgeOwner": "typApp",
			"memKnowledgeTags": {
				"tagValtype": "tagValtypeLink"
			},
			"memMemberLinkType": "agtStreamProvider"
		},
		"memAppStreamPortal": {
			"memKnowledgeType": "typMember",
			"memKnowledgeOwner": "typApp",
			"memKnowledgeTags": {
				"tagValtype": "tagValtypeLink"
			},
			"memMemberLinkType": "agtStreamPortal"
		},
		"memAppApi": {
			"memKnowledgeType": "typMember",
			"memKnowledgeOwner": "typApp",
			"memKnowledgeTags": {
				"tagValtype": "tagValtypeLink"
			},
			"memMemberLinkType": "typModule"
		},
		"memAppModules": {
			"memKnowledgeType": "typMember",
			"memKnowledgeOwner": "typApp",
			"memKnowledgeTags": {
				"tagColl": "tagCollSet",
				"tagValtype": "tagValtypeLink"
			},
			"memMemberLinkType": "typModule"
		},

		"_End_": "____________"
	}
]